fgddem/__main__.py
fgddem_py-0.1.1.dist-info/METADATA
fgddem_py-0.1.1.dist-info/WHEEL
fgddem_py-0.1.1.dist-info/entry_points.txt
fgddem_py-0.1.1.dist-info/RECORD
